quapp_qsharp/__init__.py
quapp_qsharp/async_tasks/__init__.py
quapp_qsharp/async_tasks/qsharp_circuit_export_task.py
quapp_qsharp/component/__init__.py
quapp_qsharp/component/backend/__init__.py
quapp_qsharp/component/backend/qsharp_invocation.py
quapp_qsharp/factory/__init__.py
quapp_qsharp/factory/qsharp_device_factory.py
quapp_qsharp/factory/qsharp_handler_factory.py
quapp_qsharp/factory/qsharp_provider_factory.py
quapp_qsharp/handler/__init__.py
quapp_qsharp/handler/invocation_handler.py
quapp_qsharp/model/__init__.py
quapp_qsharp/model/device/__init__.py
quapp_qsharp/model/device/azure_quantum_qsharp_device.py
quapp_qsharp/model/device/quapp_qsharp_device.py
quapp_qsharp/model/provider/__init__.py
quapp_qsharp/model/provider/azure_quantum_qsharp_provider.py
quapp_qsharp/model/provider/qapp_qsharp_provider.py
quapp_qsharp-0.0.1.dev2.dist-info/licenses/LICENSE
quapp_qsharp-0.0.1.dev2.dist-info/METADATA
quapp_qsharp-0.0.1.dev2.dist-info/WHEEL
quapp_qsharp-0.0.1.dev2.dist-info/top_level.txt
quapp_qsharp-0.0.1.dev2.dist-info/RECORD
